penbot-1.0.2.dist-info/licenses/LICENSE
src/__init__.py
src/agents/__init__.py
src/agents/base.py
src/agents/compliance.py
src/agents/coordinator.py
src/agents/encoding.py
src/agents/enhanced_generation.py
src/agents/impersonation.py
src/agents/info_disclosure.py
src/agents/jailbreak.py
src/agents/output_security.py
src/agents/rag_poisoning.py
src/agents/token_soup.py
src/agents/tool_exploit.py
src/agents/evolutionary/agent.py
src/agents/evolutionary/mutator.py
src/agents/evolutionary/token_soup_mutator.py
src/agents/subagents/__init__.py
src/agents/subagents/base.py
src/agents/subagents/domain_adaptation.py
src/agents/subagents/encoding.py
src/agents/subagents/factory.py
src/agents/subagents/psychological.py
src/agents/subagents/stealth.py
src/agents/subagents/visual.py
src/analysis/__init__.py
src/analysis/base.py
src/analysis/canned_response_detector.py
src/analysis/data_leakage.py
src/analysis/data_poisoning.py
src/analysis/excessive_agency.py
src/analysis/fitness.py
src/analysis/image_attack_detection.py
src/analysis/jailbreak_detection.py
src/analysis/llm_finding_assessor.py
src/analysis/orchestrator.py
src/analysis/policy_violation.py
src/analysis/rag_detection.py
src/analysis/structure_parser.py
src/analysis/structured_disclosure_detector.py
src/analysis/system_prompt_disclosure.py
src/analysis/target_fingerprinting.py
src/analysis/tool_detection.py
src/analysis/unbounded_consumption.py
src/analysis/vector_weaknesses.py
src/api/__init__.py
src/api/main.py
src/api/routes/__init__.py
src/api/routes/reports.py
src/api/routes/websocket.py
src/campaign/__init__.py
src/campaign/planner.py
src/cli/agents_cmd.py
src/cli/config_loader.py
src/cli/dashboard_cmd.py
src/cli/main.py
src/cli/patterns.py
src/cli/reporter.py
src/cli/sessions.py
src/cli/test_runner.py
src/cli/validator.py
src/cli/wizard.py
src/connectors/__init__.py
src/connectors/api_connector.py
src/connectors/base.py
src/connectors/factory.py
src/connectors/playwright_connector.py
src/connectors/rest_connector.py
src/connectors/web_connector.py
penbot-1.0.2.dist-info/METADATA
penbot-1.0.2.dist-info/WHEEL
penbot-1.0.2.dist-info/entry_points.txt
penbot-1.0.2.dist-info/top_level.txt
penbot-1.0.2.dist-info/RECORD
