Metadata-Version: 2.4
Name: penbot
Version: 1.0.2
Summary: AI Chatbot Penetration Testing Framework
Author: terminal48
License: MIT
Project-URL: Homepage, https://gitlab.com/yan-ban/penbot
Project-URL: Documentation, https://gitlab.com/yan-ban/penbot/-/tree/main/docs
Project-URL: Repository, https://gitlab.com/yan-ban/penbot
Project-URL: Issues, https://gitlab.com/yan-ban/penbot/-/issues
Requires-Python: >=3.11
License-File: LICENSE
Requires-Dist: langgraph>=0.2.0
Requires-Dist: langchain>=0.2.0
Requires-Dist: langchain-anthropic>=0.1.0
Requires-Dist: pydantic>=2.7.0
Requires-Dist: pydantic-settings>=2.2.0
Requires-Dist: click>=8.1.7
Requires-Dist: rich>=13.7.1
Requires-Dist: aiohttp>=3.9.4
Requires-Dist: httpx>=0.27.0
Requires-Dist: pyyaml>=6.0
Requires-Dist: python-dateutil>=2.9.0
Requires-Dist: jsonpath-ng>=1.6.0
Requires-Dist: jinja2>=3.1.3
Requires-Dist: python-dotenv>=1.0.1
Requires-Dist: structlog>=24.1.0
Provides-Extra: full
Requires-Dist: fastapi>=0.110.0; extra == "full"
Requires-Dist: uvicorn[standard]>=0.29.0; extra == "full"
Requires-Dist: playwright>=1.43.0; extra == "full"
Requires-Dist: weasyprint>=62.0; extra == "full"
Requires-Dist: reportlab>=4.1.0; extra == "full"
Requires-Dist: python-docx>=1.1.0; extra == "full"
Provides-Extra: dev
Requires-Dist: pytest>=8.1.1; extra == "dev"
Requires-Dist: pytest-asyncio>=0.23.6; extra == "dev"
Requires-Dist: pytest-cov>=5.0.0; extra == "dev"
Requires-Dist: black>=24.3.0; extra == "dev"
Requires-Dist: ruff>=0.3.5; extra == "dev"
Dynamic: license-file
